{
  "main": {
    "id": "23b27ed0e83c84cd",
    "type": "split",
    "children": [
      {
        "id": "1758db303fb638ac",
        "type": "tabs",
        "children": [
          {
            "id": "f22c6a5a25b579df",
            "type": "leaf",
            "state": {
              "type": "markdown",
              "state": {
                "file": "AZURE/README.md",
                "mode": "source",
                "source": false
              },
              "icon": "lucide-file",
              "title": "README"
            }
          }
        ]
      }
    ],
    "direction": "vertical"
  },
  "left": {
    "id": "a0f50557226278c2",
    "type": "split",
    "children": [
      {
        "id": "33ef984b129759bf",
        "type": "tabs",
        "children": [
          {
            "id": "85c8721f6c2eb4bb",
            "type": "leaf",
            "state": {
              "type": "file-explorer",
              "state": {
                "sortOrder": "alphabetical",
                "autoReveal": false
              },
              "icon": "lucide-folder-closed",
              "title": "Explorador de archivos"
            }
          },
          {
            "id": "34db568b5edb7c7f",
            "type": "leaf",
            "state": {
              "type": "search",
              "state": {
                "query": "",
                "matchingCase": false,
                "explainSearch": false,
                "collapseAll": false,
                "extraContext": false,
                "sortOrder": "alphabetical"
              },
              "icon": "lucide-search",
              "title": "Buscar"
            }
          },
          {
            "id": "ab6065fc99688334",
            "type": "leaf",
            "state": {
              "type": "bookmarks",
              "state": {},
              "icon": "lucide-bookmark",
              "title": "Marcadores"
            }
          }
        ]
      }
    ],
    "direction": "horizontal",
    "width": 300
  },
  "right": {
    "id": "b52cb93362f55c4e",
    "type": "split",
    "children": [
      {
        "id": "92eb3fbe70936529",
        "type": "tabs",
        "children": [
          {
            "id": "fd15a2bbbc75804a",
            "type": "leaf",
            "state": {
              "type": "backlink",
              "state": {
                "file": "AZURE/README.md",
                "collapseAll": false,
                "extraContext": false,
                "sortOrder": "alphabetical",
                "showSearch": false,
                "searchQuery": "",
                "backlinkCollapsed": false,
                "unlinkedCollapsed": true
              },
              "icon": "links-coming-in",
              "title": "Enlaces entrantes de README"
            }
          },
          {
            "id": "d1fb8d76964a9ed4",
            "type": "leaf",
            "state": {
              "type": "outgoing-link",
              "state": {
                "file": "AZURE/README.md",
                "linksCollapsed": false,
                "unlinkedCollapsed": true
              },
              "icon": "links-going-out",
              "title": "Enlaces salientes de README"
            }
          },
          {
            "id": "f54ba5f3dd276909",
            "type": "leaf",
            "state": {
              "type": "tag",
              "state": {
                "sortOrder": "frequency",
                "useHierarchy": true,
                "showSearch": false,
                "searchQuery": ""
              },
              "icon": "lucide-tags",
              "title": "Etiquetas"
            }
          },
          {
            "id": "22efee7112b45826",
            "type": "leaf",
            "state": {
              "type": "all-properties",
              "state": {
                "sortOrder": "frequency",
                "showSearch": false,
                "searchQuery": ""
              },
              "icon": "lucide-archive",
              "title": "Todas las propiedades"
            }
          },
          {
            "id": "2a09ecdfc0f3ee0c",
            "type": "leaf",
            "state": {
              "type": "outline",
              "state": {
                "file": "AZURE/README.md",
                "followCursor": false,
                "showSearch": false,
                "searchQuery": ""
              },
              "icon": "lucide-list",
              "title": "Esquema de README"
            }
          }
        ]
      }
    ],
    "direction": "horizontal",
    "width": 300,
    "collapsed": true
  },
  "left-ribbon": {
    "hiddenItems": {
      "switcher:Abrir selector rápido": false,
      "graph:Abrir vista gráfica": false,
      "canvas:Crear nuevo lienzo": false,
      "daily-notes:Abrir la nota de hoy": false,
      "templates:Insertar plantilla": false,
      "command-palette:Abrir paleta de comandos": false,
      "bases:Crear nueva base": false
    }
  },
  "active": "85c8721f6c2eb4bb",
  "lastOpenFiles": [
    "AZURE/scripts/ex_entraId.ps1.md",
    "AZURE/docs/ex_entraId.md",
    "AZURE/docs/get_token.md",
    "AZURE/docs/recon.md",
    "AZURE/docs/entraId.md",
    "AZURE/docs/get-token.md",
    "AZURE/docs/entra-id-actions.md",
    "AZURE/docs/entra-id-deep-dive.md",
    "AZURE/docs/recon-tenant.md",
    "AZURE/scripts/recon.ps1.md",
    "AZURE/scripts/entraId.ps1.md",
    "AZURE/scripts/get_token.ps1.md",
    "AZURE/README.md",
    "AZURE/docs/manual-reference.md",
    "Sin nombre",
    "AZURE/scripts/recon-tenant.ps1",
    "AZURE/scripts/get-token.ps1",
    "AZURE/scripts/entra-id-deep-dive.ps1",
    "AZURE/scripts/entra-id-actions.ps1",
    "AZURE/scripts",
    "AZURE/examples/recon-tenant.examples.ps1",
    "AZURE/examples/get-token.examples.ps1",
    "AZURE/examples/entra-id-deep-dive.examples.ps1",
    "AZURE/examples/entra-id-actions.examples.ps1"
  ]
}